LICENCE.txt
MANIFEST.in
README.rst
setup.py
emencia_recipe_drdump/__init__.py
emencia_recipe_drdump/recipe_interface.py
emencia_recipe_drdump.egg-info/PKG-INFO
emencia_recipe_drdump.egg-info/SOURCES.txt
emencia_recipe_drdump.egg-info/dependency_links.txt
emencia_recipe_drdump.egg-info/entry_points.txt
emencia_recipe_drdump.egg-info/not-zip-safe
emencia_recipe_drdump.egg-info/requires.txt
emencia_recipe_drdump.egg-info/top_level.txt