Metadata-Version: 1.1
Name: emencia-recipe-drdump
Version: 0.3.1
Summary: 
